[
    {
        "title": "关于 LoveIt",
        "uri": "about.zh-cn",
        "content": "LoveIt   far fa heart        Dillon              Hugo              LeaveIt      KeepIt            SEO   fas fa rocket          Google PageSpeed Insights    99 100          100 100           fab fa searchengin        JSON LD      SEO SCHEMA      SEO      fab fa google      Google Analytics   fas fa search                Google  Bind  Yandex Baidu    fas fa tachometer alt             CDN   fas fa cloud download alt      lazysizes                    fas fa desktop       fas fa mobile           fas fa moon       fas fa sun                fas fa layer group               fas fa ellipsis h          far fa list alt                  fas fa language               fab fa css3 alt       CSS              far fa user      Gravatar      fas fa user circle            far fa id card        59         fas fa share square        28         far fa comment      Disqus        far fa comment dots      Gitalk        far fa comment alt      Valine        far fa comments      Facebook             fas fa code            far fa images        lightgallery js         fab fa font awesome      Font Awesome       Markdown      far fa sticky note             Markdown      fas fa square root alt           KaTeX           fas fa project diagram        mermaid     shortcode   fas fa chart pie        ECharts           shortcode   fas fa music        APlayer   MetingJS        shortcode   fas fa tv      Bilibili    shortcode   far fa bell           shortcode   fas fa align left            shortcode   fas fa i cursor        TypeIt       shortcode   fas fa arrow down        Smooth Scroll                LoveIt    MIT                 LICENSE     LoveIt                     Font Awesome Fork Awesome Animate css lazysizes lightgallery js Smooth Scroll TypeIt    KaTeX   mermaid ECharts APlayer MetingJS Gitalk Valine",
        "objectID": "about.zh-cn",
        "date": "2019-08-02T03:04:49.000Z",
        "draft": false,
        "math": true,
        "lightgallery": true
    },
    {
        "title": "文档",
        "uri": "categories/documentation",
        "content": "",
        "objectID": "categories/documentation",
        "slug": "documentation"
    },
    {
        "weight": 4,
        "uri": "posts/basic-markdown-syntax.zh-cn",
        "content": "Hugo           Markdown                           Grav             Loveit       Markdown           Markdown                    Web         WYSIWYG                                                                       Markdown          HTML                 Markdown                               Markdown                     XHTML                                                 Markdown            Markdown          John Gruber  Markdown           Markdown                           Markdown                                             Markdown               HTML              Markdown                              John Gruber               Markdown            HTML            far fa bookmark                         1      h2   h6                    markdown h2    h3    h4    h5    h6          HTML          html h2    h3    h4    h5    h6                    ID                 ID          markdown           custom id        HTML          html                2         HTML       html              3     HTML                                     Markdown                      _                                               4                          HTML                      markdown Lorem ipsum dolor sit amet  graecis denique ei vel  duo primis mandamus  Et legere ocurreret pri  animal tacimates complectitur ad cum  Cu eum inermis inimicus efficiendi  Labore officiis ex  soluta officiis concludaturque ei qui  vide sensibus vim ad        HTML          html Lorem ipsum dolor sit amet  graecis denique ei vel  duo primis mandamus  Et legere ocurreret pri  animal tacimates complectitur ad cum  Cu eum inermis inimicus efficiendi  Labore officiis ex  soluta officiis concludaturque ei qui  vide sensibus vim ad                   5    HTML            HTML                           html Markdown           HTML Markdown          6                                         markdown                   HTML          html                                           markdown                   HTML          html                 GFM   GitHub flavored Markdown             markdown                                        HTML          html                                       markdown                                                                                HTML          html                                  7                                        markdown   Fusion Drive combines hard drive flash storage  solid state drive  presents single logical volume space drives combined                 Fusion Drive combines hard drive flash storage  solid state drive  presents single logical volume space drives combined      HTML          html Fusion Drive combines hard drive flash storage  solid state drive  presents single logical volume space drives combined              markdown   Donec massa lacus  ultricies ullamcorper in  fermentum sed augue  Nunc augue augue  aliquam non hendrerit ac  commodo vel nisi     Sed adipiscing elit vitae augue consectetur gravida nunc vehicula  Donec auctor odio non est accumsan facilisis  Aliquam id turpis dolor tincidunt mollis ac eu diam                 Donec massa lacus  ultricies ullamcorper in  fermentum sed augue  Nunc augue augue  aliquam non hendrerit ac  commodo vel nisi     Sed adipiscing elit vitae augue consectetur gravida nunc vehicula  Donec auctor odio non est accumsan facilisis  Aliquam id turpis dolor tincidunt mollis ac eu diam  8                                                        markdown                       markdown Lorem ipsum dolor sit amet Consectetur adipiscing elit Integer molestie lorem massa Facilisis pretium nisl aliquet Nulla volutpat aliquam velit Phasellus iaculis neque Purus sodales ultricies Vestibulum laoreet porttitor sem Ac tristique libero volutpat Faucibus porta lacus fringilla vel Aenean sit amet erat nunc Eget porttitor lorem              Lorem ipsum dolor sit amet Consectetur adipiscing elit Integer molestie lorem massa Facilisis pretium nisl aliquet Nulla volutpat aliquam velit Phasellus iaculis neque Purus sodales ultricies Vestibulum laoreet porttitor sem Ac tristique libero volutpat Faucibus porta lacus fringilla vel Aenean sit amet erat nunc Eget porttitor lorem     HTML          html Lorem ipsum dolor sit amet Consectetur adipiscing elit Integer molestie lorem massa Facilisis pretium nisl aliquet Nulla volutpat aliquam velit Phasellus iaculis neque Purus sodales ultricies Vestibulum laoreet porttitor sem Ac tristique libero volutpat Faucibus porta lacus fringilla vel Aenean sit amet erat nunc Eget porttitor lorem                               markdown Lorem ipsum dolor sit amet Consectetur adipiscing elit Integer molestie lorem massa Facilisis pretium nisl aliquet Nulla volutpat aliquam velit Faucibus porta lacus fringilla vel Aenean sit amet erat nunc Eget porttitor lorem              Lorem ipsum dolor sit amet Consectetur adipiscing elit Integer molestie lorem massa Facilisis pretium nisl aliquet Nulla volutpat aliquam velit Faucibus porta lacus fringilla vel Aenean sit amet erat nunc Eget porttitor lorem     HTML          html Lorem ipsum dolor sit amet Consectetur adipiscing el",
        "objectID": "posts/basic-markdown-syntax.zh-cn",
        "title": "Markdown 基本语法",
        "subtitle": "",
        "date": "2019-12-01T13:57:40.000Z",
        "lastmod": "2020-01-01T08:45:40.000Z",
        "draft": false,
        "author": "Dillon",
        "authorLink": "https://dillonzq.com",
        "description": "这篇文章展示了基本的 Markdown 语法和格式.",
        "license": "",
        "tags": [
            "markdown"
        ],
        "categories": [
            "markdown"
        ],
        "hiddenFromHomePage": true,
        "featuredImage": "/images/basic-markdown-syntax/featured-image.png",
        "featuredImagePreview": "",
        "toc": true,
        "autoCollapseToc": true,
        "math": false,
        "lightgallery": true,
        "linkToMarkdown": true,
        "share": {
            "enable": true
        },
        "comment": true
    },
    {
        "weight": 5,
        "uri": "posts/emoji-support.zh-cn",
        "content": "Emoji           Hugo        emojify                       Shortcodes        emoji                 enableEmoji   true                 emoji                      emoji        markdown           tent                  joy                      tent               joy  Emoji      Emoji       emoji                                                                       grinning    grinning    smiley    smiley      smile    smile    grin    grin      laughing    laughing satisfied    sweatsmile    sweatsmile      rofl    rofl    joy    joy      slightlysmilingface    slightlysmilingface    upsidedownface    upsidedownface      wink    wink    blush    blush      innocent    innocent                                                           hearteyes    hearteyes    kissingheart    kissingheart      kissing    kissing    relaxed    relaxed      kissingclosedeyes    kissingclosedeyes    kissingsmilingeyes    kissingsmilingeyes                                                        yum    yum    stuckouttongue    stuckouttongue      stuckouttonguewinkingeye    stuckouttonguewinkingeye    stuckouttongueclosedeyes    stuckouttongueclosedeyes      moneymouthface    moneymouthface                                                            hugs    hugs    thinking    thinking                                                       zippermouthface    zippermouthface    neutralface    neutralface      expressionless    expressionless    nomouth    nomouth      smirk    smirk    unamused    unamused      rolleyes    rolleyes    grimacing    grimacing      lyingface    lyingface                                                            relieved    relieved    pensive    pensive      sleepy    sleepy    droolingface    droolingface      sleeping    sleeping                                                            mask    mask    facewiththermometer    facewiththermometer      facewithheadbandage    facewithheadbandage    nauseatedface    nauseatedface      sneezingface    sneezingface    dizzyface    dizzyface                                                         cowboyhatface    cowboyhatface                                                             sunglasses    sunglasses    nerdface    nerdface                                                        confused    confused    worried    worried      slightlyfrowningface    slightlyfrowningface    frowningface    frowningface      openmouth    openmouth    hushed    hushed      astonished    astonished    flushed    flushed      frowning    frowning    anguished    anguished      fearful    fearful    coldsweat    coldsweat      disappointedrelieved    disappointedrelieved    cry    cry      sob    sob    scream    scream      confounded    confounded    persevere    persevere      disappointed    disappointed    sweat    sweat      weary    weary    tiredface    tiredface                                                        triumph    triumph    pout    pout rage      angry    angry    smilingimp    smilingimp      imp    imp    skull    skull      skullandcrossbones    skullandcrossbones                                                              hankey    hankey poop shit    clownface    clownface      japaneseogre    japaneseogre    japanesegoblin    japanesegoblin      ghost    ghost    alien    alien      spaceinvader    spaceinvader    robot    robot                                                       smileycat    smileycat    smilecat    smilecat      joycat    joycat    hearteyescat    hearteyescat      smirkcat    smirkcat    kissingcat    kissingcat      screamcat    screamcat    cryingcatface    cryingcatface      poutingcat    poutingcat                                                           seenoevil    seenoevil    hearnoevil    hearnoevil      speaknoevil    speaknoevil                                                         kiss    kiss    loveletter    loveletter      cupid    cupid    giftheart    giftheart      sparklingheart    sparklingheart    heartpulse    heartpulse      heartbeat    heartbeat    revolvinghearts    revolvinghearts      twohearts    twohearts    heartdecoration    heartdecoration      heavyheartexclamation    heavyheartexclamation    brokenheart    brokenheart      heart    heart    yellowheart    yellowheart      greenheart    greenheart    blueheart    blueheart      purpleheart    purpleheart    blackheart    blackheart      100    100    anger    anger      boom    boom collision    dizzy    dizzy      sweatdrops    sweatdrops    dash    dash      hole    hole    bomb    bomb      speechballoon    speechballoon    eyespeechbubble    eyespeechbubble      rightangerbubble    rightangerbubble    thoughtballoon    thoughtballoon      zzz    zzz                                                                   wave    wave    raisedbackofhand    raisedbackofhand      raisedhandwithfingerssplayed    raisedhandwithfingerssplayed    hand    hand raised_hand      vulcansalute    vulcansalute                                                              okhand    okhand    v    v      crossedfingers    crossedfingers    metal    metal      callmehand   ",
        "objectID": "posts/emoji-support.zh-cn",
        "title": "Emoji 支持",
        "subtitle": "",
        "date": "2019-10-01T09:55:28.000Z",
        "lastmod": "2019-10-01T09:55:28.000Z",
        "draft": false,
        "author": "Dillon",
        "authorLink": "https://dillonzq.com",
        "description": "Hugo 和 LoveIt 中的 Emoji 的用法指南.",
        "license": "",
        "tags": [
            "emoji"
        ],
        "categories": [
            "markdown"
        ],
        "hiddenFromHomePage": true,
        "featuredImage": "/images/emoji-support/featured-image.jpg",
        "featuredImagePreview": "",
        "toc": true,
        "autoCollapseToc": true,
        "math": false,
        "lightgallery": true,
        "linkToMarkdown": true,
        "share": {
            "enable": true
        },
        "comment": true
    },
    {
        "title": "浏览器小技巧：通过注册表为Chromium Edge安装扩展",
        "uri": "posts/install-edge-extensions-via-registry",
        "content": "Microsoft Edge       Google       Chromium     Windows 10                     Chrome                           fa fa comment dots                        crx          IT         PC                                         Windows                          Windows 10 1909     Edge 80 0 361 57                                                                                              fa fa edit             fa fa desktop               crx                                          https   robwu nl crxviewer          crx               manifest json    version                 Show analysis    Extension ID       ID            Edge  HKEYCURRENTUSER Software Microsoft Edge Extensions          3       ID                path         crx                C  Program Files  x86  Internet Download Manager IDMGCExt crx IDM                                      version         2         6 36 5                       fa fa server                Edge        Chrome                                                HKEYCURRENTUSER Software Microsoft Edge Extensions              oogbnpmeihfgnccdnmmlgicknopghhma     ID          path updateurl path    1      updateurl   Edge    https   extensionwebstorebase edgesv net v1 crx Chrome    http   clients2 google com service update2 crx                                                        fa fa file code      reg        Windows Registry Editor Version 5 00  HKEYCURRENTUSER Software Microsoft Edge Extensions llhcnbijpnechllogkacbcjmkcgjbjfi   path   https   microsoftedge microsoft com addons detail llhcnbijpnechllogkacbcjmkcgjbjfi   update_url   https   extensionwebstorebase edgesv net v1 crx   HKEYCURRENTUSER Software Microsoft Edge Extensions ngpampappnmepgilojfohadhhmbhlaek   path   C  Program Files  x86  Internet Download Manager IDMGCExt crx   version   6 36 5              reg                           fa fa feather alt                                                    Google Chrome Dev",
        "objectID": "posts/install-edge-extensions-via-registry",
        "date": "2020-03-20T14:42:34.000Z",
        "draft": false,
        "author": "Jay",
        "authorLink": "https://weibo.com/jayyoung1/",
        "description": "本文介绍基于注册表安装在线和本地扩展的小技巧",
        "license": "CC BY-NC 4.0",
        "tags": [
            "Edge",
            "Chromium",
            "Microsoft",
            "注册表",
            "浏览器",
            "扩展"
        ],
        "categories": [
            "Windows"
        ],
        "hiddenFromHomePage": false,
        "featuredImage": "https://i.loli.net/2020/03/21/F3AEZS8p7WdYmuq.png",
        "featuredImagePreview": "",
        "toc": true,
        "autoCollapseToc": true,
        "math": true,
        "lightgallery": true,
        "linkToMarkdown": true,
        "share": {
            "enable": true
        },
        "comment": true
    },
    {
        "title": "Hugo 篇一: 在威联通 NAS 上生成博客并部署 Pages 服务",
        "uri": "posts/install-hugo-on-qnap-nas",
        "content": "Hugo      Go                    Markdown                                                   Hugo                 fa fa comment dots                      Hugo                                          Markdown                                                                   QNAP TS 453Bmini 2 8G    QTS 4 4 1 1216 hugoextended0 67 1_Linux 64bit tar gz        fa fa terminal                           QTS                                    Hugo      TS 453Bmini     hugoextended0 67 1_Linux 64bit tar gz     NAS  tar  zxvf hugoextended0 67 1_Linux 64bit tar gz     hugo          hugo                chmod  x hugo                hugo help                 lib libstdc   so 6  version GLIBCXX_3 4 21  not found                     share CACHEDEV1DATA  qpkg CodexPack usr lib x8664 linux gnu libstdc   so 6     lib libstdc   so 6    hugo    PATH         ln  sf  share CACHEDEV1DATA  qpkg CodexPack usr lib x8664 linux gnu libstdc   so 6  lib libstdc   so 6 ln  sf  your hugo path hugo  usr local bin hugo      libstdc   so 6      CodexPack                              your hugo path      hugo                            shell                                              qpkg             233so        fa fa play circle          hugo help               Hugo                hugo help hugo main command  used build Hugo site  Hugo Fast Flexible Static Site Generator built love spf13 friends Go  Complete documentation available https   gohugo io   Usage  hugo  flags  hugo  command  Available Commands  check Contains verification checks config Print site configuration convert Convert content different formats env Print Hugo version environment info gen collection several useful generators  help Help command import Import site others  list Listing various types content new Create new content site server high performance webserver version Print version number Hugo Flags   b    baseURL string hostname  and path  root  e g  https   spf13 com   D    buildDrafts include content marked draft  E    buildExpired include expired content  F    buildFuture include content publishdate future   cacheDir string filesystem path cache directory  Defaults   TMPDIR hugo_cache    cleanDestinationDir remove files destination not found static directories   config string config file  default path config yaml json toml    configDir string config dir  default  config    c    contentDir string filesystem path content directory   debug debug output  d    destination string filesystem path write files   disableKinds strings disable different kind pages  home  RSS etc     enableGitInfo add Git revision  date author info pages  e    environment string build environment   forceSyncStatic copy files when static changed    gc enable run cleanup tasks  remove unused cache files  build  h    help help hugo   i18n warnings print missing translations   ignoreCache ignores cache directory  l    layoutDir string filesystem path layout directory   log enable Logging   logFile string log File path  if set  logging enabled automatically    minify minify supported output format  HTML  XML etc     noChmod don t sync permission mode files   noTimes don t sync modification time files   path warnings print warnings duplicate target paths etc    quiet build quiet mode   renderToMemory render memory  only useful benchmark testing   s    source string filesystem path read files relative   templateMetrics display metrics template executions   templateMetricsHints calculate improvement hints when combined   templateMetrics  t    theme strings themes use  located  themes THEMENAME     themesDir string filesystem path themes directory   trace file write trace file  not useful general   v    verbose verbose output   verboseLog verbose logging  w    watch watch filesystem changes recreate needed Use  hugo  command    help  information command         fa fa magic                       hugo new site  your site path your site name cd  your site path your site name ls        your site path your site name                        your site name         archetypes     markdown              content                        data                 layouts        content                       layouts    static      js css            themes                      config toml            fa fa download        LoveIt              Hugo              LeaveIt      KeepIt     LoveIt         https   github com dillonzq LoveIt                 fa fa file archive    zip           themes                       themes     git clone  b master https   github com dillonzq LoveIt git themes LoveIt                git                          git init git submodule  b master add https   github com dillonzq LoveIt git themes LoveIt   fa fa edit                    cp  f themes LoveIt exampleSite config toml config toml cp  rf themes LoveIt exampleSite static static cp  rf themes LoveIt archetypes archetypes         config toml    10        baseURL    https   example com   en  zh cn  fr       determines default content language  en  zh cn  fr               defaultContentLanguage    en  theme    theme    LoveIt  themes directory      themesDir           ",
        "objectID": "posts/install-hugo-on-qnap-nas",
        "date": "2020-03-21T10:27:28.000Z",
        "draft": false,
        "author": "Jay",
        "authorLink": "https://weibo.com/jayyoung1/",
        "description": "本文介绍如何在威联通NAS上部署hugo博客系统",
        "summary": "Hugo 是一个用 Go 语言实现的静态博客系统生成工具。基于 Markdown 撰写博文，不改变你已有的习惯，拥有快速部署、简单易用、主题丰富、易扩展等特点。你可以在任何地方启动 Hugo，实现毫秒级渲染。",
        "license": "CC BY-NC 4.0",
        "tags": [
            "QNAP",
            "hugo",
            "威联通",
            "博客",
            "NAS",
            "LoveIt"
        ],
        "categories": [
            "Hugo"
        ],
        "hiddenFromHomePage": false,
        "featuredImage": "https://i.loli.net/2020/03/21/xHuOFD5PfKhLtRg.png",
        "featuredImagePreview": "",
        "toc": true,
        "autoCollapseToc": true,
        "math": true,
        "lightgallery": true,
        "linkToMarkdown": true,
        "share": {
            "enable": true
        },
        "comment": true
    },
    {
        "title": "威联通：内网穿透解决方案之自建NPS服务",
        "uri": "posts/install-nps-on-qnap-nas",
        "content": "nps                                tcp udp            tcp udp                      ssh            dns                 http       socks5    p2p            web        fa fa comment dots                        nps frp lanproxy ngrok   zerotier                                              nps ksa              X1           nps    web         p2p                                                 QNAP TS 453Bmini 2 8G    QTS 4 4 1 1216 nps 0 26 5 Windows 10 1909 64                  fa fa info circle                                         ssh                                tcp                  dns        udp              udp            HTTP               http               ss           vpn                   socks5        fa fa star half alt                           tcp udp http s  socks5 p2p http             linux windows macos                                     https             web      https                         web ui                                                                                       header 404      host         URL                             fa fa terminal      nps                                                                       TS 453Bmini                                  https   github com ehang io nps release    TS 453Bmini                     fa fa server                      bash wget https   github com ehang io nps releases download v0 26 5 linuxamd64server tar gz mkdir nps    tar  zxvf linuxamd64server tar gz  C nps cd nps      nps install   nps                  sudo nps start stop restart                        webpassword webusername   authcryptkey   web        web         16   aes                 p2p        p2pip   p2pport      bash vi  etc nps conf nps conf                                                                                                                               web_port   web          web_password   web            web_username   web            webbaseurl   web           web                 bridge_port                  httpsproxyport        https            httpproxyport        http            auth_key   web api        bridge_type               kcp   tcp     public_vkey                                            ip_limit        ip    true   false         flowstoreinterval                                  log_level              authcryptkey         authKey    aes      16       p2p_ip       Ip    p2p          p2p_port   p2p       udp        pprof_ip   debug pprof     ip     pprof_port   debug pprof                nps  bash nps restart                nps       bash nps stop nps update update                                                                  nps            TCP 8024 8080 8001 8003 8004 UDP 6000 6002         fa fa desktop         fa fa cloud   Web    nps                                web         web         ip 8080        admin      123              webpassword webusername                                                                                                                                                                                p2p                          p2p               p2p              IP       192 168 50 100 8080                         p2p                                                               web                            fa fa power off           TS 453Bmini    npc                       wget https   github com ehang io nps releases download v0 26 6 linuxamd64client tar gz mkdir npc    cd npc   npc install  server     IP 8024  vkey         type tcp npc start     web                                 Windows                     windowsamd64client tar gz           powershell   cmd         npc              npc exe install                       cmd         bat npc  server     IP 8024  vkey         type tcp  password       target     IP                connect target failed  maybe nat type not support p2p             NAT       p2p            new conn  P2P not penetrate successfully  traffic will transferred server    p2p                                   p2p          127 0 0 1 2000   p2p                 NAT       bash npc nat  stun_addr stun stunprotocol org 3478      p2p      Symmetric Nat                    stun_addr      stun               fa fa feather alt",
        "objectID": "posts/install-nps-on-qnap-nas",
        "subtitle": "",
        "date": "2020-03-24T07:55:51.000Z",
        "lastmod": "2020-03-24T07:55:51.000Z",
        "draft": false,
        "author": "Jay",
        "authorLink": "https://weibo.com/jayyoung1/",
        "description": "本文介绍如何用NPS实现威联通内网穿透",
        "license": "",
        "tags": [
            "内网穿透",
            "威联通",
            "nps",
            "p2p"
        ],
        "categories": [
            "Nas"
        ],
        "hiddenFromHomePage": false,
        "featuredImage": "https://i.loli.net/2020/03/27/6GSN7DtBHy2J9pK.png",
        "featuredImagePreview": "",
        "toc": true,
        "autoCollapseToc": true,
        "math": true,
        "lightgallery": true,
        "linkToMarkdown": true,
        "share": {
            "enable": true
        },
        "comment": true
    },
    {
        "title": "威联通：内网穿透服务之蒲公英 X1 和 KSA",
        "uri": "posts/intranet-penetration-with-pgyx1-or-ksa",
        "content": "nps             Web                                                                          white_flower      X1     X1               Cloud VPN                                                             2233 org       ddns                                            70    X 70    X 18        CPU  MT7628A    RAM   64MB    FLASH  16MB    Micro USB        1 100 Mbps      1 USB A   1        2 4GHz 300Mbps IEEE 802 11 b g n            108         98     78                                                                                                  X1 LAN       LAN     DHCP           https   pgybox oray com     SN                      admin                                       oray            X1                                                                        X1                   VPN                                       X1                        192 168 1 0 24       192 168 1 0       255 255 255 0            24             PC                   oray                4G 5G                                         NAT                p2p                                          P2P            UPNP   X1                    2M                                                earth_asia  KSA KAS                           Windows MacOS   Linux  x86  x64  arm64 mipsel      KSA                                      computer  Windows           ksa_win exe     KSA           KSA ID          KSA ID                            computer  MacOS   Windows                           KSA        KSA ID                                   computer  Linux        sudo chmod  x ksa     ksa                   bash chmod  x ksa    ksa_x64              KSA ID   PSK                 ksa log                        Linux          ksa conf               ksa               x64      killall  9 ksa_x64                    KSA ID   PSK       uid     psk                                             ksa_x64                        IP      192 168 1                                                                                     KSA ID                                  KSA ID           Windows                    MacOS                        p2p     NAT         KSA       p2p                                   p2p          KSA     NAT                                         AES 256 CFB                             NAT                                                             memo                                                          X1             Linux   MacOS        KSA                  KSA                          https   ksa kanxue com index down htm",
        "objectID": "posts/intranet-penetration-with-pgyx1-or-ksa",
        "subtitle": "",
        "date": "2020-03-27T08:28:47.000Z",
        "lastmod": "2020-03-27T08:28:47.000Z",
        "draft": false,
        "author": "Jay",
        "authorLink": "https://weibo.com/jayyoung1/",
        "description": "本文介绍蒲公英 X1 和 KSA 如何打通外网访问内网资源",
        "license": "",
        "tags": [
            "内网穿透",
            "威联通",
            "蒲公英",
            "ksa",
            "贝锐科技"
        ],
        "categories": [
            "Nas"
        ],
        "hiddenFromHomePage": false,
        "featuredImage": "https://i.loli.net/2020/03/31/tkKaQmYTlw5pSvZ.png",
        "featuredImagePreview": "",
        "toc": true,
        "autoCollapseToc": true,
        "math": true,
        "lightgallery": true,
        "linkToMarkdown": true,
        "share": {
            "enable": true
        },
        "comment": true
    },
    {
        "title": "威联通：“私人定制”在线代码编辑器",
        "uri": "posts/qnap-codeserver-self-host",
        "content": "code server       Visual Studio Code                                             code server      3 0 Pre release                         fa fa comment dots                                         QNAP TS 453Bmini 2 8G    QTS 4 4 1 1216 code server 1 41 1 chinese language pack 1 41 0         docker   code server                                   codercom code server        linuxserver code server   xiumu code server zh cn                                                                    fa fa terminal                           QTS                                    fa fa download                code server     Release            linux arm64    linux x86_64          NAS      code server                        SSH     NAS        code server           SSH                  vscode                   code server        1 41 1      1 41 0                        F12                             https   marketplace visualstudio com _apis public gallery publishers MS CEINTL vsextensions vscode language pack zh hans  vspackage               code server   install extension          code server   uninstall extension extesion id    local share code server extensions               code server             code server  h        fa fa file code        codes erver    SSH      code server    SSH                                  shell                             ssl                 8080                   port               cert    cert key      ssl              TrustAsia         auth password             export PASSWORD  your own password             bin sh        code server                code server           vscode       https   marketplace visualstudio com    code server   install extension      code server  v      code server  log            info     critical    error   warn    info    debug    trace    off 7             local code server logs          code server        code server  h case   1  start  sudo   code server   locale zh cn   auth none    dev null    stop  sudo killall  9 code server    dev null    restart   0 stop  0 start       echo  Usage   0  start stop restart   exit 1 esac exit 0         daemon_mgr conf                   NAS                                       QTS             etc config crontab                   0 0          restart    dev null crontab            QTS      autorun sh             NAS         QTS                        BashIT               QDK     qpkg     daemon_mgr code server start     start     dev null    NAS             code server      http    8080              fa fa feather alt           Windows      vscode        userprofile   vscode      extensions           local share code server                         code server                                      local share code server logs           https   github com cdr code server issues                             IDE                              B",
        "objectID": "posts/qnap-codeserver-self-host",
        "date": "2020-03-21T07:39:58.000Z",
        "draft": "flase",
        "author": "Jay",
        "authorLink": "https://weibo.com/jayyoung1/",
        "description": "本文介绍如何在威联通NAS上部署自己的vscode编辑器",
        "license": "CC BY-NC 4.0",
        "tags": [
            "QNAP",
            "vscode",
            "威联通",
            "codeserver",
            "NAS"
        ],
        "categories": [
            "Nas"
        ],
        "hiddenFromHomePage": false,
        "featuredImage": "https://i.loli.net/2020/03/21/fJTWe25iobw7uXM.png",
        "featuredImagePreview": "",
        "toc": true,
        "autoCollapseToc": true,
        "math": true,
        "lightgallery": true,
        "linkToMarkdown": true,
        "share": {
            "enable": true
        },
        "comment": true
    },
    {
        "weight": 1,
        "uri": "posts/theme-documentation-basics.zh-cn",
        "content": "Hugo   LoveIt                  1       Hugo         Hugo                            Windows  Linux  macOS          far fa file archive   Hugo extended    0 62 0           Markdown          Hugo                      0 62 0   Hugo                         SCSS     CSS     Hugo extended              2                             Hugo                            2 1        Hugo       new               bash hugo new site my_website cd my_website   2 2      LoveIt         https   github com dillonzq LoveIt                  far fa file archive    zip           themes                       themes      bash git clone  b master https   github com dillonzq LoveIt git themes LoveIt                  git                           bash git init git submodule  b master add https   github com dillonzq LoveIt git themes LoveIt   2 3        basic configuration      LoveIt           toml baseURL    http   example org    en  zh cn  fr               defaultContentLanguage    zh cn             CN    languageCode    zh CN            hasCJKLanguage   true      title         Hugo          Hugo              theme    LoveIt   params  LoveIt      version    0 1 X   menu    menu main   identifier    posts             HTML                    pre      name        url     posts                           title      weight   1   menu main   identifier    tags  pre      name        url     tags   title      weight   2   menu main   identifier    categories  pre      name        url     categories   title      weight   3                        theme                         config toml                    2 4                           bash hugo new posts first_post md                                                                                       draft  true         draft  false       2 5                      bash hugo serve       http   localhost 1313            hugo serve                                2 6                             bash hugo         public                                    Web                     Netlify                 Netlify    HUGO                         AWS Amplify  Github pages  Render              3    3 1        site configuration     Hugo                 LoveIt                            config toml                                                toml  params  LoveIt      version    0 1 X       description           Hugo           keywords     Theme    Hugo              light    dark    auto   defaultTheme    auto     git         enableGitInfo    true     gitRepo                    SRI           SRI   sha256    sha384    sha512    md5   fingerprint                 params header             fixed    normal    auto   desktopMode    fixed             fixed    normal    auto   mobileMode    auto              params footer           2019 ICP                 HTML     icp                 HTML     license    CC BY NC 4 0          params home          params home profile  enable   true Gravatar                 gravatarEmail              URL avatarURL     images avatar png             subtitle           Hugo                   typeit   true          social   true               HTML     disclaimer              params home posts  enable   true            paginate   6                 hiddenFromHomePage         defaultHiddenFromHomePage   false            params social  GitHub    xxxx  Linkedin    xxxx  Twitter    xxxx  Instagram    xxxx  Email    xxxx xxxx com  Facebook    xxxx  Telegram    xxxx  Medium    xxxx  Gitlab    xxxx  Youtubelegacy    xxxx  Youtubecustom    xxxx  Youtubechannel    xxxx  Tumblr   xxxx  Quora    xxxx  Keybase    xxxx  Pinterest    xxxx  Reddit    xxxx  Codepen    xxxx  FreeCodeCamp    xxxx  Bitbucket    xxxx  Stackoverflow    xxxx  Weibo    xxxx  Odnoklassniki    xxxx  VK    xxxx  Flickr    xxxx  Xing    xxxx  Snapchat    xxxx  Soundcloud    xxxx  Spotify    xxxx  Bandcamp    xxxx  Paypal    xxxx  Fivehundredpx    xxxx  Mix    xxxx  Goodreads    xxxx  Lastfm    xxxx  Foursquare    xxxx  Hackernews    xxxx  Kickstarter    xxxx  Patreon    xxxx  Steam    xxxx  Twitch    xxxx  Strava    xxxx  Skype    xxxx  Whatsapp    xxxx  Zhihu    xxxx  Douban    xxxx  Angellist    xxxx  Slidershare    xxxx  Jsfiddle    xxxx  Deviantart    xxxx  Behance    xxxx  Dribble    xxxx  Wordpress    xxxx  Vine    xxxx  Googlescholar    xxxx  Researchgate    xxxx  Mastodon    xxxx  MastodonPrefix    https   mastodon technology   Thingiverse    xxxx  Devto    xxxx  Gitea    xxxx  XMPP    xxxx  Matrix    xxxx  Bilibili    xxxx          params page            lightgallery lightgallery   true             Markdown      linkToMarkdown   true            params math  enable   true                                 blockLeftDelimiter      blockRightDelimiter                                     inlineLeftDelimiter      inlineRightDelimiter      KaTeX    copy_tex copyTex   true KaTeX    mhchem mhchem   true              params share  enable   true Twitter   true Facebook   true Linkedin   true Whatsapp   true Pinterest   true Tumblr   true HackerNews   true Reddit   true VK   true Buffer   true Xing   true Line   true Instapaper   true Pocket   true Digg  ",
        "objectID": "posts/theme-documentation-basics.zh-cn",
        "title": "主题文档 - 基本概念",
        "subtitle": "",
        "date": "2020-03-06T13:40:32.000Z",
        "lastmod": "2020-03-06T13:40:32.000Z",
        "draft": false,
        "author": "Dillon",
        "authorLink": "https://dillonzq.com",
        "description": "探索 Hugo - LoveIt 主题的全部内容和背后的核心概念.",
        "license": "",
        "tags": [
            "安装",
            "配置"
        ],
        "categories": [
            "documentation"
        ],
        "hiddenFromHomePage": true,
        "featuredImage": "/images/theme-documentation-basics/featured-image.jpg",
        "featuredImagePreview": "",
        "toc": true,
        "autoCollapseToc": false,
        "math": false,
        "lightgallery": true,
        "linkToMarkdown": true,
        "share": {
            "enable": true
        },
        "comment": true
    },
    {
        "weight": 2,
        "uri": "posts/theme-documentation-content.zh-cn",
        "content": "LoveIt                    1                                          content posts         content posts         md              content         content about md                static         static images screenshot png 2      Hugo              yaml  toml    json                             yaml title            subtitle     date  2020 03 04T15 58 26 08 00 lastmod  2020 03 04T15 58 26 08 00 draft  true author     authorLink     description     license     tags     categories     hiddenFromHomePage  false featuredImage     featuredImagePreview     toc  false autoCollapseToc  true math  true lightgallery  true linkToMarkdown  true share  enable  true comment  true   title        subtitle              date                              date                         lastmod               draft       true     hugo         buildDrafts  D                author        authorLink           description           license             tags         categories           hiddenFromHomePage       true                                     featuredImage           featuredImagePreview                 toc       true               autoCollapseToc       true             math       true                 lightgallery       true                     linkToMarkdown       true               Markdown        share            params share       comment       true           3      LoveIt                      Hugo                          Hugo         70                          summaryLength                  CJK                           Hugo                       hasCJKLanguage     true                                                                                                                                          summary                                       description                                                       LoveIt                                                                                                                                                                                                                                      4 Markdown             Markdown             5 Markdown        extended markdown syntax  LoveIt                      Emoji           Emoji                LoveIt       KaTeX                           params math         enable   true                 math  true                          KaTeX           TeX                                                markdown    c    pm sqrt a 2   b 2         f x   int_   infty    infty   hat f   xi  e  2  pi  xi x  d  xi                     c    pm sqrt a 2   b 2         f x   int_   infty    infty   hat f   xi  e  2  pi  xi x  d  xi                                      markdown   c    pm sqrt a 2   b 2          f x   int_   infty    infty   hat f   xi  e  2  pi  xi x  d  xi                    c    pm sqrt a 2   b 2          f x   int_   infty    infty   hat f   xi  e  2  pi  xi x  d  xi                                           Copy tex Copy tex        KaTeX                          KaTeX                  LaTeX                           params math         copyTex   true     Copy tex                             LaTeX      mhchem mhchem        KaTeX                                                  params math         mhchem   true     mhchem   markdown     ce CO2   C    2 CO         ce Hg 2     I   HgI2    I    Hg  II I4  2                       ce CO2   C    2 CO         ce Hg 2     I   HgI2    I    Hg  II I4  2               LoveIt                 Markdown        markdown  Hugo                                   Hugo                          LoveIt           Markdown        markdown               99      100                          90   100  Font Awesome LoveIt      Font Awesome                             Font Awesome             class   markdown            fas fa campground                    far fa grin tears                        fas fa campground                 far fa grin tears          escape character                        far fa grin squint tears              Markdown                                            markdown      X     X                emoji                                    markdown        joy                   joy          joy                         Hugo   issue                markdown  link         escape character               link      escape character       link",
        "objectID": "posts/theme-documentation-content.zh-cn",
        "title": "主题文档 - 内容",
        "subtitle": "",
        "date": "2020-03-05T08:30:05.000Z",
        "lastmod": "2020-03-05T08:30:05.000Z",
        "draft": false,
        "author": "Dillon",
        "authorLink": "https://dillonzq.com",
        "description": "了解如何在 LoveIt 主题中快速, 直观地创建和组织内容.",
        "license": "",
        "tags": [
            "内容",
            "markdown"
        ],
        "categories": [
            "documentation"
        ],
        "hiddenFromHomePage": true,
        "featuredImage": "/images/theme-documentation-content/featured-image.jpg",
        "featuredImagePreview": "",
        "toc": true,
        "autoCollapseToc": false,
        "math": true,
        "lightgallery": true,
        "linkToMarkdown": true,
        "share": {
            "enable": true
        },
        "comment": true
    }
]